dogu/device/__init__.py
dogu/device/appium_server.py
dogu/device/common/closable.py
dogu/device/common/const.py
dogu/device/common/device_closer.py
dogu/device/common/device_http_response.py
dogu/device/device_client.py
dogu/device/device_host_client.py
dogu/device/logger.py
dogu_device_client-1.2.0.dist-info/METADATA
dogu_device_client-1.2.0.dist-info/WHEEL
dogu_device_client-1.2.0.dist-info/RECORD
