Metadata-Version: 2.1
Name: dogu-device-client
Version: 1.2.0
Summary: Dogu's device client to control devices
Author: Dogu Technologies
Requires-Python: >=3.9,<4.0
Classifier: Programming Language :: Python :: 3
Classifier: Programming Language :: Python :: 3.9
Classifier: Programming Language :: Python :: 3.10
Classifier: Programming Language :: Python :: 3.11
Requires-Dist: dacite (==1.8.1)
Requires-Dist: requests (==2.31.0)
Requires-Dist: websockets (==11.0.3)
